{
  "id": "run_20251119080504_bfnv",
  "modelName": "",
  "questionSetId": "set_202511181143",
  "runName": "再试试",
  "runDesc": "",
  "itemIds": [
    "c4326482-e14a-4bfd-ac79-e7f369f20632",
    "f0c18bc1-cb06-48b4-8fa7-89bd5d6de1cb"
  ],
  "totalScore": 1.7,
  "dimensionScores": {
    "dim_composition": 2.5,
    "dim_lighting": 2.5,
    "dim_consistency": 0.5,
    "dim_202511181148": 3,
    "comment": 0
  },
  "startedAt": "2025-11-19T08:05:04.654Z",
  "endedAt": "2025-11-19T08:07:36.417Z",
  "overallComment": "嘻嘻哈哈"
}